anisettev3/__init__.py
anisettev3-0.1.1.dist-info/METADATA
anisettev3-0.1.1.dist-info/WHEEL
anisettev3-0.1.1.dist-info/licenses/LICENSE
anisettev3-0.1.1.dist-info/RECORD
